setup.cfg
setup.py
docs/CREDITS.txt
docs/HISTORY.txt
docs/INSTALL.txt
docs/LICENSE.GPL
docs/LICENSE.txt
docs/README.txt
docs/TODO.txt
kss/__init__.py
kss.plugin.cacheability.egg-info/PKG-INFO
kss.plugin.cacheability.egg-info/SOURCES.txt
kss.plugin.cacheability.egg-info/dependency_links.txt
kss.plugin.cacheability.egg-info/entry_points.txt
kss.plugin.cacheability.egg-info/not-zip-safe
kss.plugin.cacheability.egg-info/requires.txt
kss.plugin.cacheability.egg-info/top_level.txt
kss/plugin/__init__.py
kss/plugin/cacheability/__init__.py
kss/plugin/cacheability/config.py
kss/plugin/cacheability/configure.zcml
kss/plugin/cacheability/kss.plugin.cacheability-configure.zcml
kss/plugin/cacheability/version.txt
kss/plugin/cacheability/demo/__init__.py
kss/plugin/cacheability/demo/configure.zcml
kss/plugin/cacheability/demo/kss_cacheability_demo.css
kss/plugin/cacheability/demo/kss_cacheability_demo.kss
kss/plugin/cacheability/demo/kss_cacheability_demo.pt
kss/plugin/cacheability/demo/kss_cacheability_demo.py
kss/plugin/cacheability/demo/kss_triggereventinbinder_demo.css
kss/plugin/cacheability/demo/kss_triggereventinbinder_demo.js
kss/plugin/cacheability/demo/kss_triggereventinbinder_demo.kss
kss/plugin/cacheability/demo/kss_triggereventinbinder_demo.pt
kss/plugin/cacheability/demo/zopeconfig.py
kss/plugin/cacheability/demo/selenium_tests/README.txt
kss/plugin/cacheability/demo/selenium_tests/cacheability.html
kss/plugin/cacheability/demo/selenium_tests/triggereventinbinder.html
kss/plugin/cacheability/javascript/cacheability.js
kss/plugin/cacheability/tests/__init__.py