Metadata-Version: 1.0
Name: kss.plugin.cacheability
Version: 0.1.1
Summary: KSS transitional cacheability plugin
Home-page: http://kssproject.org
Author: KissBooth collective
Author-email: UNKNOWN
License: GPL v3
Platform: UNKNOWN
